myfunctions_farrukh90/__init__.py
myfunctions_farrukh90/math.py
myfunctions_farrukh90-0.0.15.dist-info/METADATA
myfunctions_farrukh90-0.0.15.dist-info/WHEEL
myfunctions_farrukh90-0.0.15.dist-info/top_level.txt
myfunctions_farrukh90-0.0.15.dist-info/RECORD
