Metadata-Version: 2.1
Name: myfunctions-farrukh90
Version: 0.0.15
Summary: A description of your package
Home-page: https://github.com/farrukh90/
Author: Farrukh Sadykov
Author-email: farrukhsadykov@gmail.com
License: MIT
Platform: UNKNOWN
Classifier: Programming Language :: Python :: 3
Classifier: License :: OSI Approved :: MIT License
Classifier: Operating System :: OS Independent
Requires-Python: >=3.6
